README.md
setup.py
sibilla/__init__.py
sibilla/caching.py
sibilla/callable.py
sibilla/dataset.py
sibilla/datatypes.py
sibilla/function.py
sibilla/object.py
sibilla/package.py
sibilla/procedure.py
sibilla/schema.py
sibilla/table.py
sibilla/view.py
sibilla.egg-info/PKG-INFO
sibilla.egg-info/SOURCES.txt
sibilla.egg-info/dependency_links.txt
sibilla.egg-info/requires.txt
sibilla.egg-info/top_level.txt
test/test_caching.py
test/test_callable.py
test/test_db.py
test/test_object.py
test/test_pandas.py
test/test_row.py
test/test_schema.py
test/test_table.py
test/test_view.py