Metadata-Version: 2.1
Name: sibilla
Version: 0.1.0
Summary: Python ORM for the Oracle Database
Home-page: https://github.com/P403n1x87/sibilla
Author: Gabriele N. Tornetta
Author-email: phoenix1987@gmail.com
License: UNKNOWN
Project-URL: Bug Reports, https://github.com/P403n1x87/sibilla/issues
Project-URL: Source, https://github.com/P403n1x87/sibilla
Platform: UNKNOWN
Classifier: Development Status :: 4 - Beta
Classifier: Intended Audience :: Developers
Classifier: Intended Audience :: Science/Research
Classifier: Intended Audience :: Financial and Insurance Industry
Classifier: Topic :: Database
Classifier: Topic :: Software Development
Classifier: License :: OSI Approved :: GNU General Public License v3 (GPLv3)
Classifier: Programming Language :: Python :: 3.6
